dsgrid/__init__.py
dsgrid/_version.py
dsgrid/helpers.py
dsgrid/layerstack.py
dsgrid/model.py
dsgrid/dataformat/__init__.py
dsgrid/dataformat/datafile.py
dsgrid/dataformat/datatable.py
dsgrid/dataformat/dimmap.py
dsgrid/dataformat/enumeration.py
dsgrid/dataformat/sectordataset.py
dsgrid/dataformat/upgrade.py
dsgrid/dataformat/enumeration_data/buildstock_electric_enduses.csv
dsgrid/dataformat/enumeration_data/buildstock_electric_enduses_mwh.csv
dsgrid/dataformat/enumeration_data/buildstock_enduses.csv
dsgrid/dataformat/enumeration_data/census_divisions.csv
dsgrid/dataformat/enumeration_data/census_divisions_to_census_regions.csv
dsgrid/dataformat/enumeration_data/census_divisions_to_counties.csv
dsgrid/dataformat/enumeration_data/census_divisions_to_states.csv
dsgrid/dataformat/enumeration_data/census_regions.csv
dsgrid/dataformat/enumeration_data/census_regions_to_states.csv
dsgrid/dataformat/enumeration_data/comstock_enduses.csv
dsgrid/dataformat/enumeration_data/comstock_enduses_deprecated.csv
dsgrid/dataformat/enumeration_data/comstock_enduses_v2.csv
dsgrid/dataformat/enumeration_data/comstock_sectors.csv
dsgrid/dataformat/enumeration_data/conus_counties.csv
dsgrid/dataformat/enumeration_data/conus_counties_to_counties.csv
dsgrid/dataformat/enumeration_data/conus_states.csv
dsgrid/dataformat/enumeration_data/conus_states_to_states.csv
dsgrid/dataformat/enumeration_data/conus_to_states.csv
dsgrid/dataformat/enumeration_data/counties.csv
dsgrid/dataformat/enumeration_data/counties_to_states.csv
dsgrid/dataformat/enumeration_data/counties_to_timezones.csv
dsgrid/dataformat/enumeration_data/daily2012.csv
dsgrid/dataformat/enumeration_data/daily2012_to_daytypes.csv
dsgrid/dataformat/enumeration_data/daily2012_to_seasons.csv
dsgrid/dataformat/enumeration_data/daily2012_to_weekdays.csv
dsgrid/dataformat/enumeration_data/daily2012_to_weekly2012.csv
dsgrid/dataformat/enumeration_data/day_types.csv
dsgrid/dataformat/enumeration_data/dg_enduses.csv
dsgrid_legacy_efs_api-0.4.0.dist-info/LICENSE
dsgrid_legacy_efs_api-0.4.0.dist-info/METADATA
dsgrid_legacy_efs_api-0.4.0.dist-info/WHEEL
dsgrid_legacy_efs_api-0.4.0.dist-info/top_level.txt
dsgrid_legacy_efs_api-0.4.0.dist-info/RECORD
