Metadata-Version: 2.1
Name: dsgrid-legacy-efs-api
Version: 0.4.0
Summary: Python API for accessing demand-side grid model (dsgrid) data produced for the Electrification Futures Study (EFS)
Home-page: https://github.com/dsgrid/dsgrid-legacy-efs-api
Author: NREL
Author-email: elaine.hale@nrel.gov
License: BSD-3
Platform: UNKNOWN
Classifier: Intended Audience :: Science/Research
Classifier: License :: OSI Approved :: BSD License
Classifier: Natural Language :: English
Classifier: Programming Language :: Python
Classifier: Programming Language :: Python :: 3.6
Classifier: Programming Language :: Python :: 3.7
Classifier: Programming Language :: Python :: 3.8
Classifier: Programming Language :: Python :: 3.9
Requires-Python: >=3.6
Requires-Dist: h5py
Requires-Dist: layerstack
Requires-Dist: numpy
Requires-Dist: pandas
Requires-Dist: webcolors
Provides-Extra: dev
Requires-Dist: ghp-import ; extra == 'dev'
Requires-Dist: numpydoc ; extra == 'dev'
Requires-Dist: pandoc ; extra == 'dev'
Requires-Dist: sphinx ; extra == 'dev'
Requires-Dist: sphinx-rtd-theme ; extra == 'dev'
Requires-Dist: pytest ; extra == 'dev'
Provides-Extra: export
Requires-Dist: pyspark ; extra == 'export'
Provides-Extra: ntbks
Requires-Dist: jupyter ; extra == 'ntbks'
Requires-Dist: matplotlib ; extra == 'ntbks'
Provides-Extra: oedi
Requires-Dist: h5pyd ; extra == 'oedi'
Requires-Dist: s3fs ; extra == 'oedi'
